idcardgenerator/__init__.py
idcardgenerator/gui.py
idcardgenerator/usedres/empty.png
idcardgenerator/usedres/fzhei.ttf
idcardgenerator/usedres/hei.ttf
idcardgenerator/usedres/ico.icns
idcardgenerator/usedres/ocrb10bt.ttf
idcardgenerator-0.0.2.dist-info/LICENSE
idcardgenerator-0.0.2.dist-info/METADATA
idcardgenerator-0.0.2.dist-info/WHEEL
idcardgenerator-0.0.2.dist-info/top_level.txt
idcardgenerator-0.0.2.dist-info/RECORD
